asciicells
