Metadata-Version: 1.1
Name: asciicells
Version: 0.9.2
Summary: A Simple ASCII Table Generator
Home-page: https://github.com/mitnk/asciicells
Author: mitnk
Author-email: w@mitnk.com
License: MIT
Keywords: ascii table generator
Platform: UNKNOWN
Classifier: Development Status :: 4 - Beta
Classifier: Intended Audience :: Developers
Classifier: Topic :: Software Development :: Build Tools
Classifier: License :: OSI Approved :: MIT License
Classifier: Programming Language :: Python :: 2.7
Classifier: Programming Language :: Python :: 3
Classifier: Programming Language :: Python :: 3.4
Classifier: Programming Language :: Python :: 3.5
